ioka/__init__.py
ioka/client.py
ioka/errors.py
ioka/schemas.py
ioka-1.1.3.dist-info/DESCRIPTION.rst
ioka-1.1.3.dist-info/METADATA
ioka-1.1.3.dist-info/RECORD
ioka-1.1.3.dist-info/WHEEL
ioka-1.1.3.dist-info/metadata.json
ioka-1.1.3.dist-info/top_level.txt
