Metadata-Version: 2.0
Name: ioka
Version: 1.1.3
Summary: IOKA Asynchronous Python Client Library
Home-page: https://github.com/mortilele/ioka-python-sdk
Author: Alik Akhmetov
Author-email: ali.mars.99@gmail.com
License: MIT license
Platform: UNKNOWN
Classifier: License :: OSI Approved :: MIT License
Classifier: Programming Language :: Python :: 3.7
Classifier: Operating System :: OS Independent
Requires-Python: >=3.7
Requires-Dist: rest-aiohttp
